odoo/addons/fleet_vehicle_inspection/README.rst
odoo/addons/fleet_vehicle_inspection/__init__.py
odoo/addons/fleet_vehicle_inspection/__manifest__.py
odoo/addons/fleet_vehicle_inspection/data/fleet_vehicle_inspection.xml
odoo/addons/fleet_vehicle_inspection/demo/fleet_vehicle_inspection.xml
odoo/addons/fleet_vehicle_inspection/i18n/es.po
odoo/addons/fleet_vehicle_inspection/i18n/fleet_vehicle_inspection.pot
odoo/addons/fleet_vehicle_inspection/i18n/it.po
odoo/addons/fleet_vehicle_inspection/i18n/pt_BR.po
odoo/addons/fleet_vehicle_inspection/models/__init__.py
odoo/addons/fleet_vehicle_inspection/models/fleet_vehicle.py
odoo/addons/fleet_vehicle_inspection/models/fleet_vehicle_inspection.py
odoo/addons/fleet_vehicle_inspection/models/fleet_vehicle_inspection_item.py
odoo/addons/fleet_vehicle_inspection/models/fleet_vehicle_inspection_line.py
odoo/addons/fleet_vehicle_inspection/models/fleet_vehicle_inspection_line_image.py
odoo/addons/fleet_vehicle_inspection/readme/CONFIGURE.rst
odoo/addons/fleet_vehicle_inspection/readme/CONTRIBUTORS.rst
odoo/addons/fleet_vehicle_inspection/readme/CREDITS.rst
odoo/addons/fleet_vehicle_inspection/readme/DESCRIPTION.rst
odoo/addons/fleet_vehicle_inspection/readme/ROADMAP.rst
odoo/addons/fleet_vehicle_inspection/security/fleet_vehicle_inspection.xml
odoo/addons/fleet_vehicle_inspection/security/fleet_vehicle_inspection_item.xml
odoo/addons/fleet_vehicle_inspection/security/fleet_vehicle_inspection_line.xml
odoo/addons/fleet_vehicle_inspection/security/fleet_vehicle_inspection_line_image.xml
odoo/addons/fleet_vehicle_inspection/static/description/banner.png
odoo/addons/fleet_vehicle_inspection/static/description/icon.png
odoo/addons/fleet_vehicle_inspection/static/description/index.html
odoo/addons/fleet_vehicle_inspection/static/src/scss/backend.scss
odoo/addons/fleet_vehicle_inspection/tests/__init__.py
odoo/addons/fleet_vehicle_inspection/tests/test_fleet_vehicle_inspection.py
odoo14_addon_fleet_vehicle_inspection-14.0.3.1.0.dist-info/METADATA
odoo14_addon_fleet_vehicle_inspection-14.0.3.1.0.dist-info/WHEEL
odoo14_addon_fleet_vehicle_inspection-14.0.3.1.0.dist-info/top_level.txt
odoo14_addon_fleet_vehicle_inspection-14.0.3.1.0.dist-info/RECORD
